python_social_auth-0.3.5.dist-info/DESCRIPTION.rst
python_social_auth-0.3.5.dist-info/METADATA
python_social_auth-0.3.5.dist-info/RECORD
python_social_auth-0.3.5.dist-info/WHEEL
python_social_auth-0.3.5.dist-info/metadata.json
python_social_auth-0.3.5.dist-info/top_level.txt
social/__init__.py
social/actions.py
social/exceptions.py
social/p3.py
social/store.py
social/utils.py
social/apps/__init__.py
social/apps/cherrypy_app/__init__.py
social/apps/cherrypy_app/models.py
social/apps/cherrypy_app/utils.py
social/apps/cherrypy_app/views.py
social/apps/django_app/__init__.py
social/apps/django_app/context_processors.py
social/apps/django_app/middleware.py
social/apps/django_app/tests.py
social/apps/django_app/urls.py
social/apps/django_app/utils.py
social/apps/django_app/views.py
social/apps/django_app/default/__init__.py
social/apps/django_app/default/admin.py
social/apps/django_app/default/config.py
social/apps/django_app/default/fields.py
social/apps/django_app/default/managers.py
social/apps/django_app/default/migrations.py
social/apps/django_app/default/models.py
social/apps/django_app/default/tests.py
social/apps/django_app/default/south_migrations/0001_initial.py
social/apps/django_app/default/south_migrations/__init__.py
social/apps/django_app/me/__init__.py
social/apps/django_app/me/config.py
social/apps/django_app/me/models.py
social/apps/django_app/me/tests.py
social/apps/flask_app/__init__.py
social/apps/flask_app/routes.py
social/apps/flask_app/template_filters.py
social/apps/flask_app/utils.py
social/apps/flask_app/default/__init__.py
social/apps/flask_app/default/models.py
social/apps/flask_app/me/__init__.py
social/apps/flask_app/me/models.py
social/apps/flask_app/peewee/__init__.py
social/apps/flask_app/peewee/models.py
social/apps/pyramid_app/__init__.py
social/apps/pyramid_app/models.py
social/apps/pyramid_app/utils.py
social/apps/pyramid_app/views.py
social/apps/tornado_app/__init__.py
social/apps/tornado_app/handlers.py
social/apps/tornado_app/models.py
social/apps/tornado_app/routes.py
social/apps/tornado_app/utils.py
social/apps/webpy_app/__init__.py
social/apps/webpy_app/app.py
social/apps/webpy_app/models.py
social/apps/webpy_app/utils.py
