Metadata-Version: 2.0
Name: python-social-auth
Version: 0.3.5
Summary: Python social authentication made simple.
Home-page: https://github.com/omab/python-social-auth
Author: Matias Aguirre
Author-email: matiasaguirre@gmail.com
License: BSD
Keywords: django,flask,pyramid,webpy,openid,oauth,social auth
Platform: UNKNOWN
Classifier: Development Status :: 4 - Beta
Classifier: Topic :: Internet
Classifier: License :: OSI Approved :: BSD License
Classifier: Intended Audience :: Developers
Classifier: Environment :: Web Environment
Classifier: Programming Language :: Python
Classifier: Programming Language :: Python :: 2.7
Classifier: Programming Language :: Python :: 3
Requires-Dist: social-auth-core
Provides-Extra: cherrypy
Requires-Dist: social-auth-app-cherrypy; extra == 'cherrypy'
Provides-Extra: django
Requires-Dist: social-auth-app-django; extra == 'django'
Provides-Extra: django-mongoengine
Requires-Dist: social-auth-app-django-mongoengine; extra == 'django-mongoengine'
Provides-Extra: flask
Requires-Dist: social-auth-app-flask; extra == 'flask'
Requires-Dist: social-auth-app-flask-sqlalchemy; extra == 'flask'
Provides-Extra: flask-mongoengine
Requires-Dist: social-auth-app-flask-mongoengine; extra == 'flask-mongoengine'
Provides-Extra: flask-peewee
Requires-Dist: social-auth-app-flask-peewee; extra == 'flask-peewee'
Provides-Extra: pyramid
Requires-Dist: social-auth-app-pyramid; extra == 'pyramid'
Provides-Extra: tornado
Requires-Dist: social-auth-app-tornado; extra == 'tornado'
Provides-Extra: webpy
Requires-Dist: social-auth-app-webpy; extra == 'webpy'
